{
    "__arquivo_origem": "Conrado II do Sacro Império Romano-Germânico.html",
    "Reinado": "8 de setembro de 1024 a 4 de junho de 1039",
    "Antecessor(a)": "Rodolfo III",
    "Sucessor(a)": "Henrique III",
    "Coroação": "8 de setembro de 1024",
    "Predecessor(a)": "Henrique II",
    "Nascimento": "990 Speyer, Baixa Lorena, Sacro Império Romano-Germânico",
    "Morte": "4 de junho de 1039 (49 anos) Utrecht, Germânia, Sacro Império Romano-Germânico",
    "Sepultado em": "Catedral de Speyer, Speyer, Alemanha",
    "Esposa": "Gisela da Suábia",
    "Descendência": "Henrique III, Imperador Romano-Germânico Matilde da Francônia",
    "Dinastia": "Saliana",
    "Pai": "Henrique, Conde de Speyer",
    "Mãe": "Adelaide da Alsácia",
    "Religião": "Catolicismo"
}