{
    "__arquivo_origem": "Hortênsia de Beauharnais.html",
    "Reinado": "5 de junho de 1806 a 1 de julho de 1810",
    "Sucessora": "Guilhermina da Prússia",
    "Nascimento": "10 de abril de 1783 Paris, França",
    "Morte": "5 de outubro de 1837 (54 anos) Arenenberg, Turgóvia, Suíça",
    "Sepultado em": "Igreja de Saint-Pierre-Saint Paul, Rueil-Malmaison, França",
    "Nome completo": "Hortênsia Eugênia Cecília",
    "Marido": "Luís I da Holanda",
    "Descendência": "Napoleão Carlos Bonaparte, Príncipe Real Luís II da Holanda Napoleão III de França Charles de Morny, 1.º Duque de Morny (ilegítimo)",
    "Casa": "Beauharnais (por nascimento) Bonaparte (por casamento)",
    "Pai": "Alexandre de Beauharnais",
    "Mãe": "Josefina de Beauharnais",
    "Religião": "Catolicismo",
    "Brasão": ""
}