{
    "__arquivo_origem": "Paulina Bonaparte.html",
    "Reinado": "24 de março de 1806 a 14 de agosto de 1806",
    "Nascimento": "20 de outubro de 1780 Casa Buonaparte, Ajaccio, Córsega",
    "Morte": "9 de junho de 1825 (44 anos) Florença, Toscana, Itália",
    "Sepultado em": "Basílica de Santa Maria Maior, Roma, Itália",
    "Nome completo": "",
    "Cônjuge": "Charles Leclerc Camilo Borghese, 6.° Príncipe de Sulmona",
    "Descendência": "Dermide Leclerc",
    "Casa": "Bonaparte (por nascimento) Leclerc (1 casamento) Borghese (2 casamento)",
    "Pai": "Carlo Maria Bonaparte",
    "Mãe": "Maria Letícia Ramolino",
    "Religião": "Catolicismo",
    "Assinatura": "",
    "Brasão": ""
}