{
    "__arquivo_origem": "Sri Lanka.html",
    "Capital": "Seri Jaiavardenapura-Cota 6° 54′ N, 79° 59′ L",
    "Maior cidade": "Colombo",
    "Língua oficial": "cingalês e tâmil",
    "Línguas reconhecidas": "inglês",
    "Gentílico": "cingalês, srilankês, srilanquês",
    "Governo": "República semipresidencialista",
    "• Presidente": "Anura Kumara Dissanayake",
    "• Primeira-ministra": "Harini Amarasuriya",
    "• Presidente do Parlamento": "Asoka Ranwala",
    "• Presidente do Supremo Tribunal de Justiça": "Murdu Fernando",
    "• Data": "4 de fevereiro de 1948",
    "• República": "22 de maio de 1972",
    "• Total": "US$ 319,791 bilhões",
    "• Água (%)": "4,4",
    "• Estimativa para 2018": "21,670,000 hab. (53.º)",
    "• Densidade": "305 hab./km² (24.º)",
    "PIB (base PPC)": "Estimativa para 2019",
    "• Per capita": "US$ 14,743",
    "IDH (2021)": "0,782 (73.º) – alto",
    "Moeda": "Rupia cingalesa (LKR)",
    "Fuso horário": "(UTC +5:30)",
    "• Verão (DST)": "não observado (UTC +5:30)",
    "Cód. ISO": "LKA",
    "Cód. Internet": ".lk",
    "Cód. telef.": "+94",
    "Website governamental": "www.gov.lk"
}