{
    "__arquivo_origem": "Kosovo.html",
    "Capital e maior cidade": "Pristina 42° 40′ N, 21° 10′ L",
    "Língua oficial": "albanês e sérvio",
    "Gentílico": "kosovar, cosovar ou cossovar",
    "Governo": "República parlamentarista",
    "• Presidente": "Vjosa Osmani",
    "• Primeiro-ministro": "Albin Kurti",
    "• Declarada": "17 de fevereiro de 2008",
    "• Total": "US$ 27,66 (155.º)",
    "• Água (%)": "5,2",
    "• Estimativa para 2022": "1 761 985 hab. (151.º)",
    "• Densidade": "250 hab./km²",
    "PIB (base PPC)": "Estimativa para 2023",
    "• Per capita": "US$ 5 641 (104.º)",
    "IDH (2017)": "0,739 (94.º) – alto",
    "Moeda": "Euro ² (EUR)",
    "Fuso horário": "(UTC +1)",
    "• Verão (DST)": "CEST (UTC +2)",
    "Cód. telef.": "+383 (01.01.2015) / em 2014 : 381"
}